pyhasse.acm-0.2.8-py3.7-nspkg.pth
pyhasse/acm/__init__.py
pyhasse/acm/calc.py
pyhasse.acm-0.2.8.dist-info/AUTHORS.rst
pyhasse.acm-0.2.8.dist-info/LICENSE
pyhasse.acm-0.2.8.dist-info/METADATA
pyhasse.acm-0.2.8.dist-info/WHEEL
pyhasse.acm-0.2.8.dist-info/namespace_packages.txt
pyhasse.acm-0.2.8.dist-info/top_level.txt
pyhasse.acm-0.2.8.dist-info/RECORD
