Metadata-Version: 2.1
Name: pyhasse.acm
Version: 0.2.8
Summary: pyhasse-acm: Analysis of conflicts due to the object related indicators (horizontal evaluation).
Home-page: https://pyhasse.org
Author: Rainer Bruggemann
Author-email: rainer.bruggemann@pyhasse.org
License: MIT license
Download-URL: https://gitlab.com/pyhasse/acm
Keywords: acm
Platform: UNKNOWN
Classifier: Development Status :: 2 - Pre-Alpha
Classifier: Intended Audience :: Developers
Classifier: Intended Audience :: Science/Research
Classifier: Topic :: Scientific/Engineering :: Mathematics
Classifier: License :: OSI Approved :: MIT License
Classifier: Natural Language :: English
Classifier: Programming Language :: Python :: 3.7
Requires-Dist: setuptools
Requires-Dist: pyhasse.core
